llama_index/llms/baseten/BUILD
llama_index/llms/baseten/__init__.py
llama_index/llms/baseten/base.py
llama_index/llms/baseten/utils.py
llama_index_llms_baseten-0.1.7.dist-info/METADATA
llama_index_llms_baseten-0.1.7.dist-info/WHEEL
llama_index_llms_baseten-0.1.7.dist-info/licenses/LICENSE
llama_index_llms_baseten-0.1.7.dist-info/RECORD
