Metadata-Version: 2.4
Name: llama-index-llms-baseten
Version: 0.1.7
Summary: llama-index llms baseten integration
Author: alexker
License-Expression: MIT
License-File: LICENSE
Requires-Python: <4.0,>=3.9
Requires-Dist: llama-index-core<0.15,>=0.14.3
Requires-Dist: llama-index-llms-openai<0.7,>=0.6.0
